README.md
oms
setup.cfg
setup.py
openms/__init__.py
openms/core.py
openms/default.py
openms/docx.py
openms/outline.py
openms/query.py
openms/rtf.py
openms/template.py
openms.egg-info/PKG-INFO
openms.egg-info/SOURCES.txt
openms.egg-info/dependency_links.txt
openms.egg-info/requires.txt
openms.egg-info/top_level.txt
openms/html/__init__.py
openms/html/blockquote.py
openms/html/code.py
openms/html/converter.py
openms/html/dispatcher.py
openms/html/div.py
openms/html/emphasis.py
openms/html/heading.py
openms/html/linebreak.py
openms/html/link.py
openms/html/list_item.py
openms/html/paragraph.py
openms/html/rule.py
openms/html/strong.py
openms/html/tag.py