Metadata-Version: 2.1
Name: openms
Version: 3.5.2
Summary: A minimal implementation of OpenManuscript capabilities.
Home-page: https://github.com/openmanuscript/openmanuscript
Author: David H. Rogers
Author-email: david@dhrogers.com
License: UNKNOWN
Platform: UNKNOWN
Classifier: Programming Language :: Python :: 3
Classifier: License :: OSI Approved :: BSD License
Classifier: Operating System :: OS Independent
Requires-Python: >=3.6
